{
  "required": true,
  "minVersion": "0.8",
  "package": "nikita.uniquescythe.mixin",
  "compatibilityLevel": "JAVA_17",
  "mixins": [
    "LivingEntityMixin",
    "ExampleMixin",
    "ModifySweepingParticle",
    "ModifyCritParticle",
    "ShapedRecipeMixin",
    "ArmorFeatureRendererMixin",
    "PlayerInputMixin",
    "MovementPreventionMixin"
  ],
  "client": [
    "ItemRendererAccessor",
    "ItemRendererMixin",
    "ModelLoaderMixin",
    "ClientPlayNetworkHandlerMixin",
    "BipedEntityModelMixin",
    "PlayerEntityRendererMixin"
  ],
  "injectors": {
    "defaultRequire": 1
  }
}
